[
  {
    "type": "console.page/route",
    "properties": {
      "exact": true,
      "path": "/cryostat/",
      "component": { "$codeRef": "DashboardPage" }
    }
  },
  {
    "type": "console.page/route",
    "properties": {
      "exact": true,
      "path": "/cryostat/d-solo",
      "component": { "$codeRef": "DashboardSoloPage" }
    }
  },
  {
    "type": "console.page/route",
    "properties": {
      "exact": true,
      "path": "/cryostat/topology",
      "component": { "$codeRef": "TopologyPage" }
    }
  },
  {
    "type": "console.page/route",
    "properties": {
      "exact": true,
      "path": "/cryostat/topology/create-custom-target",
      "component": { "$codeRef": "CreateTargetPage" }
    }
  },
  {
    "type": "console.page/route",
    "properties": {
      "exact": true,
      "path": "/cryostat/rules",
      "component": { "$codeRef": "AutomatedRulesPage" }
    }
  },
  {
    "type": "console.page/route",
    "properties": {
      "exact": true,
      "path": "/cryostat/rules/create",
      "component": { "$codeRef": "CreateRulesPage" }
    }
  },
  {
    "type": "console.page/route",
    "properties": {
      "exact": true,
      "path": "/cryostat/recordings",
      "component": { "$codeRef": "RecordingsPage" }
    }
  },
  {
    "type": "console.page/route",
    "properties": {
      "exact": true,
      "path": "/cryostat/recordings/create",
      "component": { "$codeRef": "CreateRecordingPage" }
    }
  },
  {
    "type": "console.page/route",
    "properties": {
      "exact": true,
      "path": "/cryostat/archives",
      "component": { "$codeRef": "ArchivesPage" }
    }
  },
  {
    "type": "console.page/route",
    "properties": {
      "exact": true,
      "path": "/cryostat/events",
      "component": { "$codeRef": "EventsPage" }
    }
  },
  {
    "type": "console.page/route",
    "properties": {
      "exact": true,
      "path": "/cryostat/instrumentation",
      "component": { "$codeRef": "InstrumentationPage" }
    }
  },
  {
    "type": "console.page/route",
    "properties": {
      "exact": true,
      "path": "/cryostat/security",
      "component": { "$codeRef": "SecurityPage" }
    }
  },
  {
    "type": "console.page/route",
    "properties": {
      "exact": true,
      "path": "/cryostat/about",
      "component": { "$codeRef": "AboutPage" }
    }
  },
  {
    "type": "console.navigation/section",
    "properties": {
      "id": "cryostat-section",
      "perspective": "admin",
      "name": "%plugin__cryostat-plugin~Cryostat%"
    }
  },
  {
    "type": "console.navigation/href",
    "properties": {
      "id": "dashboard",
      "name": "%plugin__cryostat-plugin~Navigation.Dashboard%",
      "href": "/cryostat/",
      "perspective": "admin",
      "section": "cryostat-section"
    }
  },
  {
    "type": "console.navigation/href",
    "properties": {
      "id": "topology",
      "name": "%plugin__cryostat-plugin~Navigation.Topology%",
      "href": "/cryostat/topology",
      "perspective": "admin",
      "section": "cryostat-section"
    }
  },
  {
    "type": "console.navigation/separator",
    "properties": {
      "id": "pf-separator",
      "section": "cryostat-section",
      "insertAfter": "topology"
    }
  },
  {
    "type": "console.navigation/href",
    "properties": {
      "id": "recordings",
      "name": "%plugin__cryostat-plugin~Navigation.Recordings%",
      "href": "/cryostat/recordings",
      "perspective": "admin",
      "section": "cryostat-section"
    }
  },
  {
    "type": "console.navigation/href",
    "properties": {
      "id": "archives",
      "name": "%plugin__cryostat-plugin~Navigation.Archives%",
      "href": "/cryostat/archives",
      "perspective": "admin",
      "section": "cryostat-section"
    }
  },
  {
    "type": "console.navigation/href",
    "properties": {
      "id": "events",
      "name": "%plugin__cryostat-plugin~Navigation.Events%",
      "href": "/cryostat/events",
      "perspective": "admin",
      "section": "cryostat-section"
    }
  },
  {
    "type": "console.navigation/href",
    "properties": {
      "id": "rules",
      "name": "%plugin__cryostat-plugin~Navigation.Automated_Rules%",
      "href": "/cryostat/rules",
      "perspective": "admin",
      "section": "cryostat-section"
    }
  },
  {
    "type": "console.navigation/href",
    "properties": {
      "id": "instrumentation",
      "name": "%plugin__cryostat-plugin~Navigation.Instrumentation%",
      "href": "/cryostat/instrumentation",
      "perspective": "admin",
      "section": "cryostat-section"
    }
  },
  {
    "type": "console.navigation/separator",
    "properties": {
      "id": "pf-separator",
      "section": "cryostat-section",
      "insertAfter": "instrumentation"
    }
  },
  {
    "type": "console.navigation/href",
    "properties": {
      "id": "security",
      "name": "%plugin__cryostat-plugin~Navigation.Security%",
      "href": "/cryostat/security",
      "perspective": "admin",
      "section": "cryostat-section"
    }
  },
  {
    "type": "console.navigation/href",
    "properties": {
      "id": "about",
      "name": "%plugin__cryostat-plugin~Navigation.About%",
      "href": "/cryostat/about",
      "perspective": "admin",
      "section": "cryostat-section"
    }
  }
]
